marko_namo/__init__.py
marko_namo/go_daddy.py
marko_namo/marko_namo.py
marko_namo/utils.py
marko_namo-0.3.0.dist-info/LICENSE
marko_namo-0.3.0.dist-info/WHEEL
marko_namo-0.3.0.dist-info/METADATA
marko_namo-0.3.0.dist-info/RECORD
