Metadata-Version: 2.1
Name: marko-namo
Version: 0.3.0
Summary: Markov chain project name generator
Home-page: https://github.com/diabolical-ninja/Marko-Namo
License: MIT
Author: Yass Eltahir
Author-email: 15998949+diabolical-ninja@users.noreply.github.com
Requires-Python: >=3.8,<4.0
Classifier: License :: OSI Approved :: MIT License
Classifier: Programming Language :: Python :: 3
Classifier: Programming Language :: Python :: 3.10
Classifier: Programming Language :: Python :: 3.8
Classifier: Programming Language :: Python :: 3.9
Requires-Dist: PyYAML (>=6.0,<7.0)
Requires-Dist: requests (>=2.28.1,<3.0.0)
Project-URL: Repository, https://github.com/diabolical-ninja/Marko-Namo
